[
  {
    "name": "Age of Engineering",
    "contents": [
      {
        "version": "1.1.2",
        "windows": {
          "url": "https://modpack-1257209710.cos.ap-guangzhou.myqcloud.com/Age%20of%20Engineering-1.1.2-windows.zip",
          "md5": "9d7fd320720f71e7e2c39f77027ec899",
          "sha1": "451c586e147e8cf4e757c84a9df0389e554986e4"
        },
        "linux": {
          "url": "https://modpack-1257209710.cos.ap-guangzhou.myqcloud.com/Age%20of%20Engineering-1.1.2-linux.zip",
          "md5": "9d7fd320720f71e7e2c39f77027ec899",
          "sha1": "451c586e147e8cf4e757c84a9df0389e554986e4"
        },
        "author": [
          "TartaricAcid"
        ],
        "time": 1551163248
      }
    ]
  },
  {
    "name": "Exoria",
    "contents": [
      {
        "version": "1.2.1",
        "windows": {
          "url": "https://modpack-1257209710.cos.ap-guangzhou.myqcloud.com/Exoria-1.2.1-windows.zip",
          "md5": "f9fcd11b98aef434beedc2d827137bbf",
          "sha1": "63d2da1698a9db8e1417cf5e532bdabf40a89928"
        },
        "linux": {
          "url": "https://modpack-1257209710.cos.ap-guangzhou.myqcloud.com/Exoria-1.2.1-linux.zip",
          "md5": "f9fcd11b98aef434beedc2d827137bbf",
          "sha1": "63d2da1698a9db8e1417cf5e532bdabf40a89928"
        },
        "author": [
          "TartaricAcid"
        ],
        "time": 1551163248
      },
      {
        "version": "1.3.0b",
        "windows": {
          "url": "https://modpack-1257209710.cos.ap-guangzhou.myqcloud.com/Exoria-1.3.0b-windows.zip",
          "md5": "e440ae8ec31ff5469ad30d48c38e476a",
          "sha1": "b22c0b4a32f9d6657a7a5a39a114ee0a2efaed44"
        },
        "linux": {
          "url": "https://modpack-1257209710.cos.ap-guangzhou.myqcloud.com/Exoria-1.3.0b-linux.zip",
          "md5": "e440ae8ec31ff5469ad30d48c38e476a",
          "sha1": "b22c0b4a32f9d6657a7a5a39a114ee0a2efaed44"
        },
        "author": [
          "TartaricAcid"
        ],
        "time": 1551163248
      },
      {
        "version": "1.3.0c",
        "windows": {
          "url": "https://modpack-1257209710.cos.ap-guangzhou.myqcloud.com/Exoria-1.3.0c-windows.zip",
          "md5": "0acc0c1d12efc7e3acc3f077a6791653",
          "sha1": "a65ba0f6c0457d246010f0f1df18f23f4b0d56ea"
        },
        "linux": {
          "url": "https://modpack-1257209710.cos.ap-guangzhou.myqcloud.com/Exoria-1.3.0c-linux.zip",
          "md5": "0acc0c1d12efc7e3acc3f077a6791653",
          "sha1": "a65ba0f6c0457d246010f0f1df18f23f4b0d56ea"
        },
        "author": [
          "TartaricAcid"
        ],
        "time": 1551163248
      }
    ]
  },
  {
    "name": "Farming Valley",
    "contents": [
      {
        "version": "0.9.1",
        "windows": {
          "url": "https://modpack-1257209710.cos.ap-guangzhou.myqcloud.com/Farming%20Valley-0.9.1-windows.zip",
          "md5": "2c0f9be2da46d2d0c6e0e4ef2a1d9038",
          "sha1": "96ef2503533d20bba3ed3c51e92b47e7143418c3"
        },
        "linux": {
          "url": "https://modpack-1257209710.cos.ap-guangzhou.myqcloud.com/Farming%20Valley-0.9.1-linux.zip",
          "md5": "33f8573c28bbd4d89bc793f262ea530f",
          "sha1": "306c49935912e32838ce4f043db820849c69bc74"
        },
        "author": [
          "TartaricAcid"
        ],
        "time": 1551163248
      }
    ]
  },
  {
    "name": "FTB Continuum",
    "contents": [
      {
        "version": "1.3.1",
        "windows": {
          "url": "https://modpack-1257209710.cos.ap-guangzhou.myqcloud.com/FTB%20Continuum-1.3.1-windows.zip",
          "md5": "490117d16ecd124b4e8f711f87877eb0",
          "sha1": "775902185887dfcf73083379373086e98acb3057"
        },
        "linux": {
          "url": "https://modpack-1257209710.cos.ap-guangzhou.myqcloud.com/FTB%20Continuum-1.3.1-linux.zip",
          "md5": "490117d16ecd124b4e8f711f87877eb0",
          "sha1": "775902185887dfcf73083379373086e98acb3057"
        },
        "author": [
          "TartaricAcid"
        ],
        "time": 1551163248
      }
    ]
  },
  {
    "name": "FTB Interactions",
    "contents": [
      {
        "version": "1.4.1",
        "windows": {
          "url": "https://modpack-1257209710.cos.ap-guangzhou.myqcloud.com/FTB%20Interactions-1.4.1-windows.zip",
          "md5": "9eec7b4bc68584895a438d6314ef46d7",
          "sha1": "9ab7659093df799ebb48e17c1d87f00cc4eccfb6"
        },
        "linux": {
          "url": "https://modpack-1257209710.cos.ap-guangzhou.myqcloud.com/FTB%20Interactions-1.4.1-linux.zip",
          "md5": "9eec7b4bc68584895a438d6314ef46d7",
          "sha1": "9ab7659093df799ebb48e17c1d87f00cc4eccfb6"
        },
        "author": [
          "xinyuan-liu",
          "TartaricAcid"
        ],
        "time": 1556862221
      },
      {
        "version": "1.4.2",
        "windows": {
          "url": "https://modpack-1257209710.cos.ap-guangzhou.myqcloud.com/FTB%20Interactions-1.4.2-windows.zip",
          "md5": "1debf101dea7501ca7920f2e9f19c889",
          "sha1": "b4055bdf372cb1b99674965588e2f91fe3a98bb5"
        },
        "linux": {
          "url": "https://modpack-1257209710.cos.ap-guangzhou.myqcloud.com/FTB%20Interactions-1.4.2-linux.zip",
          "md5": "1debf101dea7501ca7920f2e9f19c889",
          "sha1": "b4055bdf372cb1b99674965588e2f91fe3a98bb5"
        },
        "author": [
          "TartaricAcid"
        ],
        "time": 1556944753
      },
      {
        "version": "1.5.0",
        "windows": {
          "url": "https://modpack-1257209710.cos.ap-guangzhou.myqcloud.com/FTB%20Interactions-1.5.0-windows.zip",
          "md5": "df2cff5e2c068c22d064c0dbbec933c3",
          "sha1": "02fb4e70508693b38bb063e26131374228e6400c"
        },
        "linux": {
          "url": "https://modpack-1257209710.cos.ap-guangzhou.myqcloud.com/FTB%20Interactions-1.5.0-linux.zip",
          "md5": "df2cff5e2c068c22d064c0dbbec933c3",
          "sha1": "02fb4e70508693b38bb063e26131374228e6400c"
        },
        "author": [
          "TartaricAcid",
          "xinyuan-liu"
        ],
        "time": 1556944753
      },
      {
        "version": "1.6.0",
        "windows": {
          "url": "https://modpack-1257209710.cos.ap-guangzhou.myqcloud.com/FTB%20Interactions-1.6.0-windows.zip",
          "md5": "4c25d57e1cb064789f5579bafa999b4a",
          "sha1": "ef500096e3bc39ee90e64d9909b4057e01ebfd96"
        },
        "linux": {
          "url": "https://modpack-1257209710.cos.ap-guangzhou.myqcloud.com/FTB%20Interactions-1.6.0-linux.zip",
          "md5": "4c25d57e1cb064789f5579bafa999b4a",
          "sha1": "ef500096e3bc39ee90e64d9909b4057e01ebfd96"
        },
        "author": [
          "xinyuan-liu"
        ],
        "time": 1558095636
      },
      {
        "version": "1.6.1",
        "windows": {
          "url": "https://modpack-1257209710.cos.ap-guangzhou.myqcloud.com/FTB%20Interactions-1.6.1-windows.zip",
          "md5": "716083ae9b574092dc5e2a830b0d551a",
          "sha1": "85ee797d681d1adcd57784b70dafad3375551e89"
        },
        "linux": {
          "url": "https://modpack-1257209710.cos.ap-guangzhou.myqcloud.com/FTB%20Interactions-1.6.1-linux.zip",
          "md5": "716083ae9b574092dc5e2a830b0d551a",
          "sha1": "85ee797d681d1adcd57784b70dafad3375551e89"
        },
        "author": [
          "xinyuan-liu"
        ],
        "time": 1558095264
      }
    ]
  },
  {
    "name": "FTB Presents SkyFactory 3",
    "contents": [
      {
        "version": "3.0.15",
        "windows": {
          "url": "https://modpack-1257209710.cos.ap-guangzhou.myqcloud.com/FTB%20Presents%20SkyFactory%203-3.0.15-windows.zip",
          "md5": "428e8e1090232273b62021f95e4ce1d2",
          "sha1": "40b4c66f87421f60e899cbd56ba7896eebfae9d0"
        },
        "linux": {
          "url": "https://modpack-1257209710.cos.ap-guangzhou.myqcloud.com/FTB%20Presents%20SkyFactory%203-3.0.15-linux.zip",
          "md5": "7989a705d417f8db79c4d6f181c01fea",
          "sha1": "4b0840f921abcb9b30001284e4697cec5d1327cf"
        },
        "author": [
          "TartaricAcid"
        ],
        "time": 1551163248
      }
    ]
  },
  {
    "name": "FTB Pyramid Reborn",
    "contents": [
      {
        "version": "2.1.1",
        "windows": {
          "url": "https://modpack-1257209710.cos.ap-guangzhou.myqcloud.com/FTB%20Pyramid%20Reborn-2.1.1-windows.zip",
          "md5": "eff15deb577e1ed0c12a2ca7d368849d",
          "sha1": "977be00dc0290790fb2df2375c24a030c4ee2bd3"
        },
        "linux": {
          "url": "https://modpack-1257209710.cos.ap-guangzhou.myqcloud.com/FTB%20Pyramid%20Reborn-2.1.1-linux.zip",
          "md5": "eff15deb577e1ed0c12a2ca7d368849d",
          "sha1": "977be00dc0290790fb2df2375c24a030c4ee2bd3"
        },
        "author": [
          "TartaricAcid"
        ],
        "time": 1551163248
      }
    ]
  },
  {
    "name": "FTB Sky Factory Challenges",
    "contents": [
      {
        "version": "1.1.0",
        "windows": {
          "url": "https://modpack-1257209710.cos.ap-guangzhou.myqcloud.com/FTB%20Sky%20Factory%20Challenges-1.1.0-windows.zip",
          "md5": "ffc2d36fa64d774646cf5786cfcf0bb5",
          "sha1": "ddbaab3a637c14bae084e32cb5ae8ee206b10140"
        },
        "linux": {
          "url": "https://modpack-1257209710.cos.ap-guangzhou.myqcloud.com/FTB%20Sky%20Factory%20Challenges-1.1.0-linux.zip",
          "md5": "ffc2d36fa64d774646cf5786cfcf0bb5",
          "sha1": "ddbaab3a637c14bae084e32cb5ae8ee206b10140"
        },
        "author": [
          "TartaricAcid"
        ],
        "time": 1551163248
      }
    ]
  },
  {
    "name": "Greg Block",
    "contents": [
      {
        "version": "1.2.0",
        "windows": {
          "url": "https://modpack-1257209710.cos.ap-guangzhou.myqcloud.com/Greg%20Block-1.2.0-windows.zip",
          "md5": "50e404f213790ffaf0acbb623f179fd3",
          "sha1": "1945d386a78e7323a0324e839ae73223ca2677a2"
        },
        "linux": {
          "url": "https://modpack-1257209710.cos.ap-guangzhou.myqcloud.com/Greg%20Block-1.2.0-linux.zip",
          "md5": "50e404f213790ffaf0acbb623f179fd3",
          "sha1": "1945d386a78e7323a0324e839ae73223ca2677a2"
        },
        "author": [
          "TartaricAcid"
        ],
        "time": 1551163248
      },
      {
        "version": "1.3.1",
        "windows": {
          "url": "https://modpack-1257209710.cos.ap-guangzhou.myqcloud.com/Greg%20Block-1.3.1-windows.zip",
          "md5": "44cc8946d84729f42e925b82f5cea747",
          "sha1": "b9877d5844ff0604938a897a94ff55c43e1b07a1"
        },
        "linux": {
          "url": "https://modpack-1257209710.cos.ap-guangzhou.myqcloud.com/Greg%20Block-1.3.1-linux.zip",
          "md5": "44cc8946d84729f42e925b82f5cea747",
          "sha1": "b9877d5844ff0604938a897a94ff55c43e1b07a1"
        },
        "author": [
          "TartaricAcid"
        ],
        "time": 1551163248
      },
      {
        "version": "1.3.2",
        "windows": {
          "url": "https://modpack-1257209710.cos.ap-guangzhou.myqcloud.com/Greg%20Block-1.3.2-windows.zip",
          "md5": "aaaa72243664ec06209e14c039bf7c75",
          "sha1": "81f1e715eae665e3ee45fd24e081f2b9182a3436"
        },
        "linux": {
          "url": "https://modpack-1257209710.cos.ap-guangzhou.myqcloud.com/Greg%20Block-1.3.2-linux.zip",
          "md5": "aaaa72243664ec06209e14c039bf7c75",
          "sha1": "81f1e715eae665e3ee45fd24e081f2b9182a3436"
        },
        "author": [
          "TartaricAcid"
        ],
        "time": 1551163248
      },
      {
        "version": "1.4.0",
        "windows": {
          "url": "https://modpack-1257209710.cos.ap-guangzhou.myqcloud.com/Greg%20Block-1.4.0-windows.zip",
          "md5": "303fecaabf3ebee98d7ccb1472443d81",
          "sha1": "e2b0da0501ba1c139fff029a9f52d81cf767414f"
        },
        "linux": {
          "url": "https://modpack-1257209710.cos.ap-guangzhou.myqcloud.com/Greg%20Block-1.4.0-linux.zip",
          "md5": "303fecaabf3ebee98d7ccb1472443d81",
          "sha1": "e2b0da0501ba1c139fff029a9f52d81cf767414f"
        },
        "author": [
          "TartaricAcid"
        ],
        "time": 1551163248
      },
      {
        "version": "1.4.1",
        "windows": {
          "url": "https://modpack-1257209710.cos.ap-guangzhou.myqcloud.com/Greg%20Block-1.4.1-windows.zip",
          "md5": "b57e97d9e05a7bdcf5b88ea452d0f263",
          "sha1": "e5fe3300dbc18360d34d2512a46d6cfd3cdeded1"
        },
        "linux": {
          "url": "https://modpack-1257209710.cos.ap-guangzhou.myqcloud.com/Greg%20Block-1.4.1-linux.zip",
          "md5": "b57e97d9e05a7bdcf5b88ea452d0f263",
          "sha1": "e5fe3300dbc18360d34d2512a46d6cfd3cdeded1"
        },
        "author": [
          "TartaricAcid"
        ],
        "time": 1551163248
      },
      {
        "version": "1.4.2",
        "windows": {
          "url": "https://modpack-1257209710.cos.ap-guangzhou.myqcloud.com/Greg%20Block-1.4.2-windows.zip",
          "md5": "be8fc67f04eaa65d9be694a88ae9e7e8",
          "sha1": "c24f0aa5104816f407e8eb70531ab824177bbde6"
        },
        "linux": {
          "url": "https://modpack-1257209710.cos.ap-guangzhou.myqcloud.com/Greg%20Block-1.4.2-linux.zip",
          "md5": "be8fc67f04eaa65d9be694a88ae9e7e8",
          "sha1": "c24f0aa5104816f407e8eb70531ab824177bbde6"
        },
        "author": [
          "TartaricAcid"
        ],
        "time": 1551163248
      },
      {
        "version": "1.4.3",
        "windows": {
          "url": "https://modpack-1257209710.cos.ap-guangzhou.myqcloud.com/Greg%20Block-1.4.3-windows.zip",
          "md5": "bb2d31c0776f6570a11737d77dcd18a5",
          "sha1": "40d33975e34eef7245e1497e60ec706982a59f32"
        },
        "linux": {
          "url": "https://modpack-1257209710.cos.ap-guangzhou.myqcloud.com/Greg%20Block-1.4.3-linux.zip",
          "md5": "bb2d31c0776f6570a11737d77dcd18a5",
          "sha1": "40d33975e34eef7245e1497e60ec706982a59f32"
        },
        "author": [
          "TartaricAcid"
        ],
        "time": 1551163248
      },
      {
        "version": "1.4.4",
        "windows": {
          "url": "https://modpack-1257209710.cos.ap-guangzhou.myqcloud.com/Greg%20Block-1.4.4-windows.zip",
          "md5": "47ad883aa9ab517e3940733449d6fb94",
          "sha1": "9ca976284a0067b500a8cedb0e63845e925be2c1"
        },
        "linux": {
          "url": "https://modpack-1257209710.cos.ap-guangzhou.myqcloud.com/Greg%20Block-1.4.4-linux.zip",
          "md5": "47ad883aa9ab517e3940733449d6fb94",
          "sha1": "9ca976284a0067b500a8cedb0e63845e925be2c1"
        },
        "author": [
          "TartaricAcid"
        ],
        "time": 1551163248
      },
      {
        "version": "1.4.5",
        "windows": {
          "url": "https://modpack-1257209710.cos.ap-guangzhou.myqcloud.com/Greg%20Block-1.4.5-windows.zip",
          "md5": "23ef1cee2c9045d40e158b29f9fcc7af",
          "sha1": "b35b6255a7aa325628a9f19e75bb3988c7e5bf89"
        },
        "linux": {
          "url": "https://modpack-1257209710.cos.ap-guangzhou.myqcloud.com/Greg%20Block-1.4.5-linux.zip",
          "md5": "23ef1cee2c9045d40e158b29f9fcc7af",
          "sha1": "b35b6255a7aa325628a9f19e75bb3988c7e5bf89"
        },
        "author": [
          "TartaricAcid"
        ],
        "time": 1551163248
      },
      {
        "version": "1.4.6",
        "windows": {
          "url": "https://modpack-1257209710.cos.ap-guangzhou.myqcloud.com/Greg%20Block-1.4.6-windows.zip",
          "md5": "532d4977bd5c835b30303a7f1bc69ba5",
          "sha1": "658c025e422fa9f45ffdb0a18554034ef790fc2b"
        },
        "linux": {
          "url": "https://modpack-1257209710.cos.ap-guangzhou.myqcloud.com/Greg%20Block-1.4.6-linux.zip",
          "md5": "532d4977bd5c835b30303a7f1bc69ba5",
          "sha1": "658c025e422fa9f45ffdb0a18554034ef790fc2b"
        },
        "author": [
          "TartaricAcid"
        ],
        "time": 1551163248
      },
      {
        "version": "2.2.0",
        "windows": {
          "url": "https://modpack-1257209710.cos.ap-guangzhou.myqcloud.com/Greg%20Block-2.2.0-windows.zip",
          "md5": "4721674ce81aa0e42b6c6d45cec4c4ca",
          "sha1": "f4449e26a2ecddd621c045786a36ccbca7f99323"
        },
        "linux": {
          "url": "https://modpack-1257209710.cos.ap-guangzhou.myqcloud.com/Greg%20Block-2.2.0-linux.zip",
          "md5": "4721674ce81aa0e42b6c6d45cec4c4ca",
          "sha1": "f4449e26a2ecddd621c045786a36ccbca7f99323"
        },
        "author": [
          "IIzzaya"
        ],
        "time": 1554055074
      },
      {
        "version": "2.2.1",
        "windows": {
          "url": "https://modpack-1257209710.cos.ap-guangzhou.myqcloud.com/Greg%20Block-2.2.1-windows.zip",
          "md5": "5fb2e45b1d891875dab74c4ea80fc3f1",
          "sha1": "e1995216c405ede409a2b43206c39b8cb1110d87"
        },
        "linux": {
          "url": "https://modpack-1257209710.cos.ap-guangzhou.myqcloud.com/Greg%20Block-2.2.1-linux.zip",
          "md5": "5fb2e45b1d891875dab74c4ea80fc3f1",
          "sha1": "e1995216c405ede409a2b43206c39b8cb1110d87"
        },
        "author": [
          "IIzzaya"
        ],
        "time": 1554994555
      }
    ]
  },
  {
    "name": "GT New Horizons",
    "contents": [
      {
        "version": "2.0.4.9",
        "windows": {
          "url": "https://modpack-1257209710.cos.ap-guangzhou.myqcloud.com/GT%20New%20Horizons-2.0.4.9-windows.zip",
          "md5": "1e5ea2ea061a58e8b239b260740adef1",
          "sha1": "fc21fdc59d86874a5996eef913fbf8660a99070e"
        },
        "linux": {
          "url": "https://modpack-1257209710.cos.ap-guangzhou.myqcloud.com/GT%20New%20Horizons-2.0.4.9-linux.zip",
          "md5": "1e5ea2ea061a58e8b239b260740adef1",
          "sha1": "fc21fdc59d86874a5996eef913fbf8660a99070e"
        },
        "author": [
          "TartaricAcid"
        ],
        "time": 1551163248
      },
      {
        "version": "2.0.5.1",
        "windows": {
          "url": "https://modpack-1257209710.cos.ap-guangzhou.myqcloud.com/GT%20New%20Horizons-2.0.5.1-windows.zip",
          "md5": "bb4060e6fc9c24572e6ec672bd6f5707",
          "sha1": "8b1156b5e805d2c7561b0eb5e97d98f9a70d87a0"
        },
        "linux": {
          "url": "https://modpack-1257209710.cos.ap-guangzhou.myqcloud.com/GT%20New%20Horizons-2.0.5.1-linux.zip",
          "md5": "bb4060e6fc9c24572e6ec672bd6f5707",
          "sha1": "8b1156b5e805d2c7561b0eb5e97d98f9a70d87a0"
        },
        "author": [
          "TartaricAcid"
        ],
        "time": 1551163248
      },
      {
        "version": "2.0.6.0",
        "windows": {
          "url": "https://modpack-1257209710.cos.ap-guangzhou.myqcloud.com/GT%20New%20Horizons-2.0.6.0-windows.zip",
          "md5": "fc53dc69862234caaa617198b2a84637",
          "sha1": "fe6532b457b6010c17d31b4a93f5b83c6e616c46"
        },
        "linux": {
          "url": "https://modpack-1257209710.cos.ap-guangzhou.myqcloud.com/GT%20New%20Horizons-2.0.6.0-linux.zip",
          "md5": "fc53dc69862234caaa617198b2a84637",
          "sha1": "fe6532b457b6010c17d31b4a93f5b83c6e616c46"
        },
        "author": [
          "TartaricAcid"
        ],
        "time": 1551163248
      },
      {
        "version": "2.0.6.2",
        "windows": {
          "url": "https://modpack-1257209710.cos.ap-guangzhou.myqcloud.com/GT%20New%20Horizons-2.0.6.2-windows.zip",
          "md5": "e1f60562dcc953603ce70eefa38015b6",
          "sha1": "9b2966c9fc1a10dc3ea09bb1d98a00e8b5808cde"
        },
        "linux": {
          "url": "https://modpack-1257209710.cos.ap-guangzhou.myqcloud.com/GT%20New%20Horizons-2.0.6.2-linux.zip",
          "md5": "e1f60562dcc953603ce70eefa38015b6",
          "sha1": "9b2966c9fc1a10dc3ea09bb1d98a00e8b5808cde"
        },
        "author": [
          "TartaricAcid"
        ],
        "time": 1551163248
      },
      {
        "version": "2.0.6.8",
        "windows": {
          "url": "https://modpack-1257209710.cos.ap-guangzhou.myqcloud.com/GT%20New%20Horizons-2.0.6.8-windows.zip",
          "md5": "540ccf2bee12fecc243c4c4168ec4369",
          "sha1": "c6c9376bf5dda3c478d346e754c864c6ffff1651"
        },
        "linux": {
          "url": "https://modpack-1257209710.cos.ap-guangzhou.myqcloud.com/GT%20New%20Horizons-2.0.6.8-linux.zip",
          "md5": "540ccf2bee12fecc243c4c4168ec4369",
          "sha1": "c6c9376bf5dda3c478d346e754c864c6ffff1651"
        },
        "author": [
          "TartaricAcid",
          "Kiwi233"
        ],
        "time": 1552275779
      },
      {
        "version": "2.0.7.0",
        "windows": {
          "url": "https://modpack-1257209710.cos.ap-guangzhou.myqcloud.com/GT%20New%20Horizons-2.0.7.0-windows.zip",
          "md5": "da38c5136a55f35ff56a3a41d61036b1",
          "sha1": "7f6638e4c8cacfcbbd4b9d3123c5632b8a49fa6d"
        },
        "linux": {
          "url": "https://modpack-1257209710.cos.ap-guangzhou.myqcloud.com/GT%20New%20Horizons-2.0.7.0-linux.zip",
          "md5": "da38c5136a55f35ff56a3a41d61036b1",
          "sha1": "7f6638e4c8cacfcbbd4b9d3123c5632b8a49fa6d"
        },
        "author": [
          "Kiwi233"
        ],
        "time": 1552275779
      }
    ]
  },
  {
    "name": "GT New Horizons (含魔改汉化)",
    "contents": [
      {
        "version": "2.0.4.9",
        "windows": {
          "url": "https://modpack-1257209710.cos.ap-guangzhou.myqcloud.com/GT%20New%20Horizons%20%28%E5%90%AB%E9%AD%94%E6%94%B9%E6%B1%89%E5%8C%96%29-2.0.4.9-windows.zip",
          "md5": "1b624da9a84808091905b35455ac8f05",
          "sha1": "5cc7263a36ab18d6dccb4a1c201dbf3c55914eae"
        },
        "linux": {
          "url": "https://modpack-1257209710.cos.ap-guangzhou.myqcloud.com/GT%20New%20Horizons%20%28%E5%90%AB%E9%AD%94%E6%94%B9%E6%B1%89%E5%8C%96%29-2.0.4.9-linux.zip",
          "md5": "1b624da9a84808091905b35455ac8f05",
          "sha1": "5cc7263a36ab18d6dccb4a1c201dbf3c55914eae"
        },
        "author": [
          "TartaricAcid"
        ],
        "time": 1551163248
      },
      {
        "version": "2.0.5.1",
        "windows": {
          "url": "https://modpack-1257209710.cos.ap-guangzhou.myqcloud.com/GT%20New%20Horizons%20%28%E5%90%AB%E9%AD%94%E6%94%B9%E6%B1%89%E5%8C%96%29-2.0.5.1-windows.zip",
          "md5": "35890ba256e26c2ed3e06677e46b6c94",
          "sha1": "b1acae1882b1d394b4b8c03936f821250fe36e20"
        },
        "linux": {
          "url": "https://modpack-1257209710.cos.ap-guangzhou.myqcloud.com/GT%20New%20Horizons%20%28%E5%90%AB%E9%AD%94%E6%94%B9%E6%B1%89%E5%8C%96%29-2.0.5.1-linux.zip",
          "md5": "35890ba256e26c2ed3e06677e46b6c94",
          "sha1": "b1acae1882b1d394b4b8c03936f821250fe36e20"
        },
        "author": [
          "TartaricAcid"
        ],
        "time": 1551163248
      },
      {
        "version": "2.0.6.0",
        "windows": {
          "url": "https://modpack-1257209710.cos.ap-guangzhou.myqcloud.com/GT%20New%20Horizons%20%28%E5%90%AB%E9%AD%94%E6%94%B9%E6%B1%89%E5%8C%96%29-2.0.6.0-windows.zip",
          "md5": "0b425c960e6ab62d3c0904ebdd25a170",
          "sha1": "ce85ac70971349b3602138c07128d4b1391797b0"
        },
        "linux": {
          "url": "https://modpack-1257209710.cos.ap-guangzhou.myqcloud.com/GT%20New%20Horizons%20%28%E5%90%AB%E9%AD%94%E6%94%B9%E6%B1%89%E5%8C%96%29-2.0.6.0-linux.zip",
          "md5": "0b425c960e6ab62d3c0904ebdd25a170",
          "sha1": "ce85ac70971349b3602138c07128d4b1391797b0"
        },
        "author": [
          "TartaricAcid"
        ],
        "time": 1551163248
      },
      {
        "version": "2.0.6.2",
        "windows": {
          "url": "https://modpack-1257209710.cos.ap-guangzhou.myqcloud.com/GT%20New%20Horizons%20%28%E5%90%AB%E9%AD%94%E6%94%B9%E6%B1%89%E5%8C%96%29-2.0.6.2-windows.zip",
          "md5": "eaba25b55a15de53c51e4e9ea9ad6b86",
          "sha1": "afeccaa06994695e65afb1c7b2c644c2d8f86d06"
        },
        "linux": {
          "url": "https://modpack-1257209710.cos.ap-guangzhou.myqcloud.com/GT%20New%20Horizons%20%28%E5%90%AB%E9%AD%94%E6%94%B9%E6%B1%89%E5%8C%96%29-2.0.6.2-linux.zip",
          "md5": "eaba25b55a15de53c51e4e9ea9ad6b86",
          "sha1": "afeccaa06994695e65afb1c7b2c644c2d8f86d06"
        },
        "author": [
          "TartaricAcid"
        ],
        "time": 1551163248
      },
      {
        "version": "2.0.6.8",
        "windows": {
          "url": "https://modpack-1257209710.cos.ap-guangzhou.myqcloud.com/GT%20New%20Horizons%20%28%E5%90%AB%E9%AD%94%E6%94%B9%E6%B1%89%E5%8C%96%29-2.0.6.8-windows.zip",
          "md5": "dff40cab73ae52d205daf56dea8f3b34",
          "sha1": "c981a932384fc8472af06cb961a8e64d5d0c1f6e"
        },
        "linux": {
          "url": "https://modpack-1257209710.cos.ap-guangzhou.myqcloud.com/GT%20New%20Horizons%20%28%E5%90%AB%E9%AD%94%E6%94%B9%E6%B1%89%E5%8C%96%29-2.0.6.8-linux.zip",
          "md5": "dff40cab73ae52d205daf56dea8f3b34",
          "sha1": "c981a932384fc8472af06cb961a8e64d5d0c1f6e"
        },
        "author": [
          "TartaricAcid",
          "Kiwi233"
        ],
        "time": 1552275779
      },
      {
        "version": "2.0.7.0",
        "windows": {
          "url": "https://modpack-1257209710.cos.ap-guangzhou.myqcloud.com/GT%20New%20Horizons%20%28%E5%90%AB%E9%AD%94%E6%94%B9%E6%B1%89%E5%8C%96%29-2.0.7.0-windows.zip",
          "md5": "35c43e24f113a8eaffc808068b7ef577",
          "sha1": "de62866a85971784c3df78b4a78536d8354a57f8"
        },
        "linux": {
          "url": "https://modpack-1257209710.cos.ap-guangzhou.myqcloud.com/GT%20New%20Horizons%20%28%E5%90%AB%E9%AD%94%E6%94%B9%E6%B1%89%E5%8C%96%29-2.0.7.0-linux.zip",
          "md5": "35c43e24f113a8eaffc808068b7ef577",
          "sha1": "de62866a85971784c3df78b4a78536d8354a57f8"
        },
        "author": [
          "Kiwi233"
        ],
        "time": 1552275779
      }
    ]
  },
  {
    "name": "Invasion",
    "contents": [
      {
        "version": "1.0.9",
        "windows": {
          "url": "https://modpack-1257209710.cos.ap-guangzhou.myqcloud.com/Invasion-1.0.9-windows.zip",
          "md5": "ef5b8551bc9b067437fa459bc84e195c",
          "sha1": "ca8ad54cdfe12a042b556e7d4aaf496b1be5609d"
        },
        "linux": {
          "url": "https://modpack-1257209710.cos.ap-guangzhou.myqcloud.com/Invasion-1.0.9-linux.zip",
          "md5": "ef5b8551bc9b067437fa459bc84e195c",
          "sha1": "ca8ad54cdfe12a042b556e7d4aaf496b1be5609d"
        },
        "author": [
          "TartaricAcid"
        ],
        "time": 1551163248
      }
    ]
  },
  {
    "name": "Modern Skyblock 3",
    "contents": [
      {
        "version": "3.5.0",
        "windows": {
          "url": "https://modpack-1257209710.cos.ap-guangzhou.myqcloud.com/Modern%20Skyblock%203-3.5.0-windows.zip",
          "md5": "3a4d5746703baf26068d47d21e681bec",
          "sha1": "b0322534582294f4bbc864ee098925d8b7bb719a"
        },
        "linux": {
          "url": "https://modpack-1257209710.cos.ap-guangzhou.myqcloud.com/Modern%20Skyblock%203-3.5.0-linux.zip",
          "md5": "3a4d5746703baf26068d47d21e681bec",
          "sha1": "b0322534582294f4bbc864ee098925d8b7bb719a"
        },
        "author": [
          "TartaricAcid"
        ],
        "time": 1551163248
      }
    ]
  },
  {
    "name": "Primal Skies",
    "contents": [
      {
        "version": "1.1.12",
        "windows": {
          "url": "https://modpack-1257209710.cos.ap-guangzhou.myqcloud.com/Primal%20Skies-1.1.12-windows.zip",
          "md5": "2c07aa372eea0bdb88ccd048d86c0c8c",
          "sha1": "04875c5956a08ee9ff7339a53c930cf803162b6d"
        },
        "linux": {
          "url": "https://modpack-1257209710.cos.ap-guangzhou.myqcloud.com/Primal%20Skies-1.1.12-linux.zip",
          "md5": "2c07aa372eea0bdb88ccd048d86c0c8c",
          "sha1": "04875c5956a08ee9ff7339a53c930cf803162b6d"
        },
        "author": [
          "TartaricAcid"
        ],
        "time": 1551163248
      }
    ]
  },
  {
    "name": "SevTech Ages",
    "contents": [
      {
        "version": "3.0.6",
        "windows": {
          "url": "https://modpack-1257209710.cos.ap-guangzhou.myqcloud.com/SevTech%20Ages-3.0.6-windows.zip",
          "md5": "6a08dcee32cb62efb3e0f3e01540e0ec",
          "sha1": "1964556fc56e30cbecd304fee15cd624f46e3097"
        },
        "linux": {
          "url": "https://modpack-1257209710.cos.ap-guangzhou.myqcloud.com/SevTech%20Ages-3.0.6-linux.zip",
          "md5": "b8276e418b3a6cea8275b964c468e916",
          "sha1": "f21e5931ee3fe64f73b6d5f71f345c1a452e14b1"
        },
        "author": [
          "TartaricAcid"
        ],
        "time": 1551163248
      },
      {
        "version": "3.0.7",
        "windows": {
          "url": "https://modpack-1257209710.cos.ap-guangzhou.myqcloud.com/SevTech%20Ages-3.0.7-windows.zip",
          "md5": "feae9d73e5ded4aa25c344a3076fe61d",
          "sha1": "0c1f53575dfbbdb81c5d2a2caa77185d368ff6ae"
        },
        "linux": {
          "url": "https://modpack-1257209710.cos.ap-guangzhou.myqcloud.com/SevTech%20Ages-3.0.7-linux.zip",
          "md5": "08bbc316045351426318a0bed0a24392",
          "sha1": "271cb9c13a907c6cc4975a4012d741e07f135f1b"
        },
        "author": [
          "TartaricAcid"
        ],
        "time": 1551163248
      },
      {
        "version": "3.0.8",
        "windows": {
          "url": "https://modpack-1257209710.cos.ap-guangzhou.myqcloud.com/SevTech%20Ages-3.0.8-windows.zip",
          "md5": "e684cd54f94fc4ddc504cd209f771d25",
          "sha1": "fab6c3a3719d463186f57ec1933db81ed910df2b"
        },
        "linux": {
          "url": "https://modpack-1257209710.cos.ap-guangzhou.myqcloud.com/SevTech%20Ages-3.0.8-linux.zip",
          "md5": "575f515d3577d2c271a0198a7cafdb08",
          "sha1": "1ffa05f823b3991ae60ced5c977e4b1a3dc2d202"
        },
        "author": [
          "TartaricAcid"
        ],
        "time": 1551163248
      }
    ]
  },
  {
    "name": "SkyFactory 4",
    "contents": [
      {
        "version": "4.0.2",
        "windows": {
          "url": "https://modpack-1257209710.cos.ap-guangzhou.myqcloud.com/SkyFactory%204-4.0.2-windows.zip",
          "md5": "9b9b71fd78e862c874e5f25747ef13ad",
          "sha1": "57f5de277c7f7c10506015ac71f6ea6161849455"
        },
        "linux": {
          "url": "https://modpack-1257209710.cos.ap-guangzhou.myqcloud.com/SkyFactory%204-4.0.2-linux.zip",
          "md5": "dae2c4f192808a7f4bcd17b9e7304035",
          "sha1": "d5001d1788435794dc95c33eecbbbdc221045180"
        },
        "author": [
          "TartaricAcid"
        ],
        "time": 1555934153
      },
      {
        "version": "4.0.3",
        "windows": {
          "url": "https://modpack-1257209710.cos.ap-guangzhou.myqcloud.com/SkyFactory%204-4.0.3-windows.zip",
          "md5": "eba34a98a827806d2ba20cb32dcb581b",
          "sha1": "c4b35f2b8406e907eb671b1291a70c1a3c5d4d5d"
        },
        "linux": {
          "url": "https://modpack-1257209710.cos.ap-guangzhou.myqcloud.com/SkyFactory%204-4.0.3-linux.zip",
          "md5": "1550ade8ba1a795a3d26c3b7f7a57495",
          "sha1": "8767e6fc73e26fe09151f5ad920c7601f6787ea1"
        },
        "author": [
          "TartaricAcid"
        ],
        "time": 1556276095
      },
      {
        "version": "4.0.4",
        "windows": {
          "url": "https://modpack-1257209710.cos.ap-guangzhou.myqcloud.com/SkyFactory%204-4.0.4-windows.zip",
          "md5": "df374b7b42244bc51a341caec82c753b",
          "sha1": "d4cd9dc6ad1b3eddae038d1e8ef2d4fefb5407a7"
        },
        "linux": {
          "url": "https://modpack-1257209710.cos.ap-guangzhou.myqcloud.com/SkyFactory%204-4.0.4-linux.zip",
          "md5": "f03d69505411970b359fb719ed4475a8",
          "sha1": "d0e41bc747ae60fbe5ad0eb66f48631a822b8f8a"
        },
        "author": [
          "TartaricAcid"
        ],
        "time": 1556947917
      },
      {
        "version": "4.0.5",
        "windows": {
          "url": "https://modpack-1257209710.cos.ap-guangzhou.myqcloud.com/SkyFactory%204-4.0.5-windows.zip",
          "md5": "df374b7b42244bc51a341caec82c753b",
          "sha1": "d4cd9dc6ad1b3eddae038d1e8ef2d4fefb5407a7"
        },
        "linux": {
          "url": "https://modpack-1257209710.cos.ap-guangzhou.myqcloud.com/SkyFactory%204-4.0.5-linux.zip",
          "md5": "f03d69505411970b359fb719ed4475a8",
          "sha1": "d0e41bc747ae60fbe5ad0eb66f48631a822b8f8a"
        },
        "author": [
          "TartaricAcid"
        ],
        "time": 1556949377
      }
    ]
  },
  {
    "name": "Space Astronomy 2",
    "contents": [
      {
        "version": "1.4.9",
        "windows": {
          "url": "https://modpack-1257209710.cos.ap-guangzhou.myqcloud.com/Space%20Astronomy%202-1.4.9-windows.zip",
          "md5": "b4837228a625f09dff5bdee95e1a0227",
          "sha1": "10d5e6f579030fae75fff851e9dc4b2e23f1a9fc"
        },
        "linux": {
          "url": "https://modpack-1257209710.cos.ap-guangzhou.myqcloud.com/Space%20Astronomy%202-1.4.9-linux.zip",
          "md5": "9405dc3538fed00f38c785c21d3d5828",
          "sha1": "b6c9e072e2c449b92e6d946d243d4d5689eb83d6"
        },
        "author": [
          "TartaricAcid"
        ],
        "time": 1551163248
      }
    ]
  },
  {
    "name": "Stone Block",
    "contents": [
      {
        "version": "1.0.26",
        "windows": {
          "url": "https://modpack-1257209710.cos.ap-guangzhou.myqcloud.com/Stone%20Block-1.0.26-windows.zip",
          "md5": "8e6c79b9723f580b2481b0c26992b409",
          "sha1": "ea29211b52d287cf055602019f8872a168ac23ad"
        },
        "linux": {
          "url": "https://modpack-1257209710.cos.ap-guangzhou.myqcloud.com/Stone%20Block-1.0.26-linux.zip",
          "md5": "8e6c79b9723f580b2481b0c26992b409",
          "sha1": "ea29211b52d287cf055602019f8872a168ac23ad"
        },
        "author": [
          "TartaricAcid"
        ],
        "time": 1551163248
      },
      {
        "version": "1.0.27",
        "windows": {
          "url": "https://modpack-1257209710.cos.ap-guangzhou.myqcloud.com/Stone%20Block-1.0.27-windows.zip",
          "md5": "8e6c79b9723f580b2481b0c26992b409",
          "sha1": "ea29211b52d287cf055602019f8872a168ac23ad"
        },
        "linux": {
          "url": "https://modpack-1257209710.cos.ap-guangzhou.myqcloud.com/Stone%20Block-1.0.27-linux.zip",
          "md5": "8e6c79b9723f580b2481b0c26992b409",
          "sha1": "ea29211b52d287cf055602019f8872a168ac23ad"
        },
        "author": [
          "TartaricAcid"
        ],
        "time": 1551163248
      },
      {
        "version": "1.0.28",
        "windows": {
          "url": "https://modpack-1257209710.cos.ap-guangzhou.myqcloud.com/Stone%20Block-1.0.28-windows.zip",
          "md5": "8e6c79b9723f580b2481b0c26992b409",
          "sha1": "ea29211b52d287cf055602019f8872a168ac23ad"
        },
        "linux": {
          "url": "https://modpack-1257209710.cos.ap-guangzhou.myqcloud.com/Stone%20Block-1.0.28-linux.zip",
          "md5": "8e6c79b9723f580b2481b0c26992b409",
          "sha1": "ea29211b52d287cf055602019f8872a168ac23ad"
        },
        "author": [
          "TartaricAcid"
        ],
        "time": 1551163248
      },
      {
        "version": "1.0.29",
        "windows": {
          "url": "https://modpack-1257209710.cos.ap-guangzhou.myqcloud.com/Stone%20Block-1.0.29-windows.zip",
          "md5": "8e6c79b9723f580b2481b0c26992b409",
          "sha1": "ea29211b52d287cf055602019f8872a168ac23ad"
        },
        "linux": {
          "url": "https://modpack-1257209710.cos.ap-guangzhou.myqcloud.com/Stone%20Block-1.0.29-linux.zip",
          "md5": "8e6c79b9723f580b2481b0c26992b409",
          "sha1": "ea29211b52d287cf055602019f8872a168ac23ad"
        },
        "author": [
          "TartaricAcid"
        ],
        "time": 1551163248
      },
      {
        "version": "1.0.30",
        "windows": {
          "url": "https://modpack-1257209710.cos.ap-guangzhou.myqcloud.com/Stone%20Block-1.0.30-windows.zip",
          "md5": "8e6c79b9723f580b2481b0c26992b409",
          "sha1": "ea29211b52d287cf055602019f8872a168ac23ad"
        },
        "linux": {
          "url": "https://modpack-1257209710.cos.ap-guangzhou.myqcloud.com/Stone%20Block-1.0.30-linux.zip",
          "md5": "8e6c79b9723f580b2481b0c26992b409",
          "sha1": "ea29211b52d287cf055602019f8872a168ac23ad"
        },
        "author": [
          "TartaricAcid"
        ],
        "time": 1551163248
      },
      {
        "version": "1.0.31",
        "windows": {
          "url": "https://modpack-1257209710.cos.ap-guangzhou.myqcloud.com/Stone%20Block-1.0.31-windows.zip",
          "md5": "8e6c79b9723f580b2481b0c26992b409",
          "sha1": "ea29211b52d287cf055602019f8872a168ac23ad"
        },
        "linux": {
          "url": "https://modpack-1257209710.cos.ap-guangzhou.myqcloud.com/Stone%20Block-1.0.31-linux.zip",
          "md5": "8e6c79b9723f580b2481b0c26992b409",
          "sha1": "ea29211b52d287cf055602019f8872a168ac23ad"
        },
        "author": [
          "TartaricAcid"
        ],
        "time": 1551163248
      }
    ]
  },
  {
    "name": "Stone Block 2",
    "contents": [
      {
        "version": "1.10.0",
        "windows": {
          "url": "https://modpack-1257209710.cos.ap-guangzhou.myqcloud.com/Stone%20Block%202-1.10.0-windows.zip",
          "md5": "208facc041d5733e6618c55c10fb5a28",
          "sha1": "b3feb89d48e4eb55e04ce06563cc017684e37ea2"
        },
        "linux": {
          "url": "https://modpack-1257209710.cos.ap-guangzhou.myqcloud.com/Stone%20Block%202-1.10.0-linux.zip",
          "md5": "208facc041d5733e6618c55c10fb5a28",
          "sha1": "b3feb89d48e4eb55e04ce06563cc017684e37ea2"
        },
        "author": [
          "10935336"
        ],
        "time": 1556025473
      },
      {
        "version": "1.11.0",
        "windows": {
          "url": "https://modpack-1257209710.cos.ap-guangzhou.myqcloud.com/Stone%20Block%202-1.11.0-windows.zip",
          "md5": "208facc041d5733e6618c55c10fb5a28",
          "sha1": "b3feb89d48e4eb55e04ce06563cc017684e37ea2"
        },
        "linux": {
          "url": "https://modpack-1257209710.cos.ap-guangzhou.myqcloud.com/Stone%20Block%202-1.11.0-linux.zip",
          "md5": "208facc041d5733e6618c55c10fb5a28",
          "sha1": "b3feb89d48e4eb55e04ce06563cc017684e37ea2"
        },
        "author": [
          "10935336"
        ],
        "time": 1556025473
      },
      {
        "version": "1.12.0",
        "windows": {
          "url": "https://modpack-1257209710.cos.ap-guangzhou.myqcloud.com/Stone%20Block%202-1.12.0-windows.zip",
          "md5": "208facc041d5733e6618c55c10fb5a28",
          "sha1": "b3feb89d48e4eb55e04ce06563cc017684e37ea2"
        },
        "linux": {
          "url": "https://modpack-1257209710.cos.ap-guangzhou.myqcloud.com/Stone%20Block%202-1.12.0-linux.zip",
          "md5": "208facc041d5733e6618c55c10fb5a28",
          "sha1": "b3feb89d48e4eb55e04ce06563cc017684e37ea2"
        },
        "author": [
          "10935336"
        ],
        "time": 1556966160
      },
      {
        "version": "1.3.0",
        "windows": {
          "url": "https://modpack-1257209710.cos.ap-guangzhou.myqcloud.com/Stone%20Block%202-1.3.0-windows.zip",
          "md5": "bff0eaed383a5e66b2612b1ef6a07aaa",
          "sha1": "23a30c9d70e90f4d8bc240d7553146f839bd0214"
        },
        "linux": {
          "url": "https://modpack-1257209710.cos.ap-guangzhou.myqcloud.com/Stone%20Block%202-1.3.0-linux.zip",
          "md5": "bff0eaed383a5e66b2612b1ef6a07aaa",
          "sha1": "23a30c9d70e90f4d8bc240d7553146f839bd0214"
        },
        "author": [
          "TartaricAcid",
          "10935336"
        ],
        "time": 1551420614
      },
      {
        "version": "1.4.0",
        "windows": {
          "url": "https://modpack-1257209710.cos.ap-guangzhou.myqcloud.com/Stone%20Block%202-1.4.0-windows.zip",
          "md5": "bff0eaed383a5e66b2612b1ef6a07aaa",
          "sha1": "23a30c9d70e90f4d8bc240d7553146f839bd0214"
        },
        "linux": {
          "url": "https://modpack-1257209710.cos.ap-guangzhou.myqcloud.com/Stone%20Block%202-1.4.0-linux.zip",
          "md5": "bff0eaed383a5e66b2612b1ef6a07aaa",
          "sha1": "23a30c9d70e90f4d8bc240d7553146f839bd0214"
        },
        "author": [
          "TartaricAcid",
          "10935336"
        ],
        "time": 1551420624
      },
      {
        "version": "1.5.0",
        "windows": {
          "url": "https://modpack-1257209710.cos.ap-guangzhou.myqcloud.com/Stone%20Block%202-1.5.0-windows.zip",
          "md5": "bff0eaed383a5e66b2612b1ef6a07aaa",
          "sha1": "23a30c9d70e90f4d8bc240d7553146f839bd0214"
        },
        "linux": {
          "url": "https://modpack-1257209710.cos.ap-guangzhou.myqcloud.com/Stone%20Block%202-1.5.0-linux.zip",
          "md5": "bff0eaed383a5e66b2612b1ef6a07aaa",
          "sha1": "23a30c9d70e90f4d8bc240d7553146f839bd0214"
        },
        "author": [
          "TartaricAcid",
          "10935336"
        ],
        "time": 1551420633
      },
      {
        "version": "1.6.0",
        "windows": {
          "url": "https://modpack-1257209710.cos.ap-guangzhou.myqcloud.com/Stone%20Block%202-1.6.0-windows.zip",
          "md5": "7c284b28bd7e3f7574cffbd9bb9c447c",
          "sha1": "4b0d7d13ed9ea44a7d641f3880d9e1dd482c72b5"
        },
        "linux": {
          "url": "https://modpack-1257209710.cos.ap-guangzhou.myqcloud.com/Stone%20Block%202-1.6.0-linux.zip",
          "md5": "7c284b28bd7e3f7574cffbd9bb9c447c",
          "sha1": "4b0d7d13ed9ea44a7d641f3880d9e1dd482c72b5"
        },
        "author": [
          "TartaricAcid",
          "10935336"
        ],
        "time": 1551421133
      },
      {
        "version": "1.7.0",
        "windows": {
          "url": "https://modpack-1257209710.cos.ap-guangzhou.myqcloud.com/Stone%20Block%202-1.7.0-windows.zip",
          "md5": "7c284b28bd7e3f7574cffbd9bb9c447c",
          "sha1": "4b0d7d13ed9ea44a7d641f3880d9e1dd482c72b5"
        },
        "linux": {
          "url": "https://modpack-1257209710.cos.ap-guangzhou.myqcloud.com/Stone%20Block%202-1.7.0-linux.zip",
          "md5": "7c284b28bd7e3f7574cffbd9bb9c447c",
          "sha1": "4b0d7d13ed9ea44a7d641f3880d9e1dd482c72b5"
        },
        "author": [
          "TartaricAcid",
          "10935336"
        ],
        "time": 1551421233
      },
      {
        "version": "1.8.0",
        "windows": {
          "url": "https://modpack-1257209710.cos.ap-guangzhou.myqcloud.com/Stone%20Block%202-1.8.0-windows.zip",
          "md5": "7c284b28bd7e3f7574cffbd9bb9c447c",
          "sha1": "4b0d7d13ed9ea44a7d641f3880d9e1dd482c72b5"
        },
        "linux": {
          "url": "https://modpack-1257209710.cos.ap-guangzhou.myqcloud.com/Stone%20Block%202-1.8.0-linux.zip",
          "md5": "7c284b28bd7e3f7574cffbd9bb9c447c",
          "sha1": "4b0d7d13ed9ea44a7d641f3880d9e1dd482c72b5"
        },
        "author": [
          "10935336"
        ],
        "time": 1551421382
      },
      {
        "version": "1.9.0",
        "windows": {
          "url": "https://modpack-1257209710.cos.ap-guangzhou.myqcloud.com/Stone%20Block%202-1.9.0-windows.zip",
          "md5": "208facc041d5733e6618c55c10fb5a28",
          "sha1": "b3feb89d48e4eb55e04ce06563cc017684e37ea2"
        },
        "linux": {
          "url": "https://modpack-1257209710.cos.ap-guangzhou.myqcloud.com/Stone%20Block%202-1.9.0-linux.zip",
          "md5": "208facc041d5733e6618c55c10fb5a28",
          "sha1": "b3feb89d48e4eb55e04ce06563cc017684e37ea2"
        },
        "author": [
          "10935336",
          "FormatToday"
        ],
        "time": 1553819727
      }
    ]
  }
]